yzm_util/__init__.py
yzm_util/snowflake.py
yzm_util-0.0.2.dist-info/METADATA
yzm_util-0.0.2.dist-info/WHEEL
yzm_util-0.0.2.dist-info/licenses/LICENSE
yzm_util-0.0.2.dist-info/RECORD
